eochat/__init__.py
eochat/bitutil.py
eochat/builder.py
eochat/crypto.py
eochat/periodic.py
eochat/processer.py
eochat/wrapper.py
eochat-0.3.0.dist-info/LICENSE
eochat-0.3.0.dist-info/METADATA
eochat-0.3.0.dist-info/WHEEL
eochat-0.3.0.dist-info/entry_points.txt
eochat-0.3.0.dist-info/top_level.txt
eochat-0.3.0.dist-info/RECORD
