Metadata-Version: 2.1
Name: eochat
Version: 0.3.0
Summary: A CLI chat client for Everfree Outpost
Home-page: https://gitlab.com/EO_utilities/eo-cli-chat
Author: First Last, Script Filly
Author-email: proto_anon_eo@protonmail.com, anonymous.indefinitely@gmail.com
License: GPLv3
Project-URL: Bug Tracker, https://gitlab.com/EO_utilities/eo-cli-chat/-/issues
Classifier: Programming Language :: Python :: 3
Classifier: License :: OSI Approved :: GNU General Public License v3 or later (GPLv3+)
Classifier: Operating System :: OS Independent
Requires-Python: >=3.6
License-File: LICENSE
Requires-Dist: tornado
Requires-Dist: aioconsole
Requires-Dist: toml
